{
  "schemaVersion": "v1",
  "chartType": "ei-support",
  "state": "SC",
  "totalDistricts": 7,
  "election": "2024 Presidential",
  "selectedCandidate": "Donald Trump",
  "selectedGroup": "Black",
  "units": {
    "share": "decimal_0_to_1"
  },
  "overlapPct": 0,
  "polarizationPct": 100,
  "series": [
    {
      "key": "black",
      "label": "Black",
      "confidenceScore": 0.9997,
      "points": [
        {
          "xSupportShare": 0,
          "density": 0.681909
        },
        {
          "xSupportShare": 0.0125,
          "density": 2.059927
        },
        {
          "xSupportShare": 0.025,
          "density": 4.892033
        },
        {
          "xSupportShare": 0.0375,
          "density": 9.1405
        },
        {
          "xSupportShare": 0.05,
          "density": 13.444819
        },
        {
          "xSupportShare": 0.0625,
          "density": 15.574579
        },
        {
          "xSupportShare": 0.075,
          "density": 14.210905
        },
        {
          "xSupportShare": 0.0875,
          "density": 10.212424
        },
        {
          "xSupportShare": 0.1,
          "density": 5.778152
        },
        {
          "xSupportShare": 0.1125,
          "density": 2.572526
        },
        {
          "xSupportShare": 0.125,
          "density": 0.900585
        },
        {
          "xSupportShare": 0.1375,
          "density": 0.247694
        },
        {
          "xSupportShare": 0.15,
          "density": 0.053474
        },
        {
          "xSupportShare": 0.1625,
          "density": 0.009053
        },
        {
          "xSupportShare": 0.175,
          "density": 0.001201
        },
        {
          "xSupportShare": 0.1875,
          "density": 0.000125
        },
        {
          "xSupportShare": 0.2,
          "density": 0.00001
        },
        {
          "xSupportShare": 0.2125,
          "density": 0.000001
        },
        {
          "xSupportShare": 0.225,
          "density": 0
        },
        {
          "xSupportShare": 0.2375,
          "density": 0
        },
        {
          "xSupportShare": 0.25,
          "density": 0
        },
        {
          "xSupportShare": 0.2625,
          "density": 0
        },
        {
          "xSupportShare": 0.275,
          "density": 0
        },
        {
          "xSupportShare": 0.2875,
          "density": 0
        },
        {
          "xSupportShare": 0.3,
          "density": 0
        },
        {
          "xSupportShare": 0.3125,
          "density": 0
        },
        {
          "xSupportShare": 0.325,
          "density": 0
        },
        {
          "xSupportShare": 0.3375,
          "density": 0
        },
        {
          "xSupportShare": 0.35,
          "density": 0
        },
        {
          "xSupportShare": 0.3625,
          "density": 0
        },
        {
          "xSupportShare": 0.375,
          "density": 0
        },
        {
          "xSupportShare": 0.3875,
          "density": 0
        },
        {
          "xSupportShare": 0.4,
          "density": 0
        },
        {
          "xSupportShare": 0.4125,
          "density": 0
        },
        {
          "xSupportShare": 0.425,
          "density": 0
        },
        {
          "xSupportShare": 0.4375,
          "density": 0
        },
        {
          "xSupportShare": 0.45,
          "density": 0
        },
        {
          "xSupportShare": 0.4625,
          "density": 0
        },
        {
          "xSupportShare": 0.475,
          "density": 0
        },
        {
          "xSupportShare": 0.4875,
          "density": 0
        },
        {
          "xSupportShare": 0.5,
          "density": 0
        },
        {
          "xSupportShare": 0.5125,
          "density": 0
        },
        {
          "xSupportShare": 0.525,
          "density": 0
        },
        {
          "xSupportShare": 0.5375,
          "density": 0
        },
        {
          "xSupportShare": 0.55,
          "density": 0
        },
        {
          "xSupportShare": 0.5625,
          "density": 0
        },
        {
          "xSupportShare": 0.575,
          "density": 0
        },
        {
          "xSupportShare": 0.5875,
          "density": 0
        },
        {
          "xSupportShare": 0.6,
          "density": 0
        },
        {
          "xSupportShare": 0.6125,
          "density": 0
        },
        {
          "xSupportShare": 0.625,
          "density": 0
        },
        {
          "xSupportShare": 0.6375,
          "density": 0
        },
        {
          "xSupportShare": 0.65,
          "density": 0
        },
        {
          "xSupportShare": 0.6625,
          "density": 0
        },
        {
          "xSupportShare": 0.675,
          "density": 0
        },
        {
          "xSupportShare": 0.6875,
          "density": 0
        },
        {
          "xSupportShare": 0.7,
          "density": 0
        },
        {
          "xSupportShare": 0.7125,
          "density": 0
        },
        {
          "xSupportShare": 0.725,
          "density": 0
        },
        {
          "xSupportShare": 0.7375,
          "density": 0
        },
        {
          "xSupportShare": 0.75,
          "density": 0
        },
        {
          "xSupportShare": 0.7625,
          "density": 0
        },
        {
          "xSupportShare": 0.775,
          "density": 0
        },
        {
          "xSupportShare": 0.7875,
          "density": 0
        },
        {
          "xSupportShare": 0.8,
          "density": 0
        },
        {
          "xSupportShare": 0.8125,
          "density": 0
        },
        {
          "xSupportShare": 0.825,
          "density": 0
        },
        {
          "xSupportShare": 0.8375,
          "density": 0
        },
        {
          "xSupportShare": 0.85,
          "density": 0
        },
        {
          "xSupportShare": 0.8625,
          "density": 0
        },
        {
          "xSupportShare": 0.875,
          "density": 0
        },
        {
          "xSupportShare": 0.8875,
          "density": 0
        },
        {
          "xSupportShare": 0.9,
          "density": 0
        },
        {
          "xSupportShare": 0.9125,
          "density": 0
        },
        {
          "xSupportShare": 0.925,
          "density": 0
        },
        {
          "xSupportShare": 0.9375,
          "density": 0
        },
        {
          "xSupportShare": 0.95,
          "density": 0
        },
        {
          "xSupportShare": 0.9625,
          "density": 0
        },
        {
          "xSupportShare": 0.975,
          "density": 0
        },
        {
          "xSupportShare": 0.9875,
          "density": 0
        },
        {
          "xSupportShare": 1,
          "density": 0
        }
      ]
    },
    {
      "key": "non_black",
      "label": "Non-Black",
      "confidenceScore": 0.9997,
      "points": [
        {
          "xSupportShare": 0,
          "density": 0
        },
        {
          "xSupportShare": 0.0125,
          "density": 0
        },
        {
          "xSupportShare": 0.025,
          "density": 0
        },
        {
          "xSupportShare": 0.0375,
          "density": 0
        },
        {
          "xSupportShare": 0.05,
          "density": 0
        },
        {
          "xSupportShare": 0.0625,
          "density": 0
        },
        {
          "xSupportShare": 0.075,
          "density": 0
        },
        {
          "xSupportShare": 0.0875,
          "density": 0
        },
        {
          "xSupportShare": 0.1,
          "density": 0
        },
        {
          "xSupportShare": 0.1125,
          "density": 0
        },
        {
          "xSupportShare": 0.125,
          "density": 0
        },
        {
          "xSupportShare": 0.1375,
          "density": 0
        },
        {
          "xSupportShare": 0.15,
          "density": 0
        },
        {
          "xSupportShare": 0.1625,
          "density": 0
        },
        {
          "xSupportShare": 0.175,
          "density": 0
        },
        {
          "xSupportShare": 0.1875,
          "density": 0
        },
        {
          "xSupportShare": 0.2,
          "density": 0
        },
        {
          "xSupportShare": 0.2125,
          "density": 0
        },
        {
          "xSupportShare": 0.225,
          "density": 0
        },
        {
          "xSupportShare": 0.2375,
          "density": 0
        },
        {
          "xSupportShare": 0.25,
          "density": 0
        },
        {
          "xSupportShare": 0.2625,
          "density": 0
        },
        {
          "xSupportShare": 0.275,
          "density": 0
        },
        {
          "xSupportShare": 0.2875,
          "density": 0
        },
        {
          "xSupportShare": 0.3,
          "density": 0
        },
        {
          "xSupportShare": 0.3125,
          "density": 0
        },
        {
          "xSupportShare": 0.325,
          "density": 0
        },
        {
          "xSupportShare": 0.3375,
          "density": 0
        },
        {
          "xSupportShare": 0.35,
          "density": 0
        },
        {
          "xSupportShare": 0.3625,
          "density": 0
        },
        {
          "xSupportShare": 0.375,
          "density": 0
        },
        {
          "xSupportShare": 0.3875,
          "density": 0
        },
        {
          "xSupportShare": 0.4,
          "density": 0
        },
        {
          "xSupportShare": 0.4125,
          "density": 0
        },
        {
          "xSupportShare": 0.425,
          "density": 0
        },
        {
          "xSupportShare": 0.4375,
          "density": 0
        },
        {
          "xSupportShare": 0.45,
          "density": 0
        },
        {
          "xSupportShare": 0.4625,
          "density": 0
        },
        {
          "xSupportShare": 0.475,
          "density": 0
        },
        {
          "xSupportShare": 0.4875,
          "density": 0
        },
        {
          "xSupportShare": 0.5,
          "density": 0
        },
        {
          "xSupportShare": 0.5125,
          "density": 0
        },
        {
          "xSupportShare": 0.525,
          "density": 0
        },
        {
          "xSupportShare": 0.5375,
          "density": 0
        },
        {
          "xSupportShare": 0.55,
          "density": 0
        },
        {
          "xSupportShare": 0.5625,
          "density": 0
        },
        {
          "xSupportShare": 0.575,
          "density": 0
        },
        {
          "xSupportShare": 0.5875,
          "density": 0.000001
        },
        {
          "xSupportShare": 0.6,
          "density": 0.000014
        },
        {
          "xSupportShare": 0.6125,
          "density": 0.000166
        },
        {
          "xSupportShare": 0.625,
          "density": 0.001594
        },
        {
          "xSupportShare": 0.6375,
          "density": 0.01192
        },
        {
          "xSupportShare": 0.65,
          "density": 0.06957
        },
        {
          "xSupportShare": 0.6625,
          "density": 0.316904
        },
        {
          "xSupportShare": 0.675,
          "density": 1.126786
        },
        {
          "xSupportShare": 0.6875,
          "density": 3.127422
        },
        {
          "xSupportShare": 0.7,
          "density": 6.776152
        },
        {
          "xSupportShare": 0.7125,
          "density": 11.461638
        },
        {
          "xSupportShare": 0.725,
          "density": 15.135192
        },
        {
          "xSupportShare": 0.7375,
          "density": 15.603163
        },
        {
          "xSupportShare": 0.75,
          "density": 12.558028
        },
        {
          "xSupportShare": 0.7625,
          "density": 7.890597
        },
        {
          "xSupportShare": 0.775,
          "density": 3.870511
        },
        {
          "xSupportShare": 0.7875,
          "density": 1.482117
        },
        {
          "xSupportShare": 0.8,
          "density": 0.44303
        },
        {
          "xSupportShare": 0.8125,
          "density": 0.103371
        },
        {
          "xSupportShare": 0.825,
          "density": 0.018826
        },
        {
          "xSupportShare": 0.8375,
          "density": 0.002676
        },
        {
          "xSupportShare": 0.85,
          "density": 0.000297
        },
        {
          "xSupportShare": 0.8625,
          "density": 0.000026
        },
        {
          "xSupportShare": 0.875,
          "density": 0.000002
        },
        {
          "xSupportShare": 0.8875,
          "density": 0
        },
        {
          "xSupportShare": 0.9,
          "density": 0
        },
        {
          "xSupportShare": 0.9125,
          "density": 0
        },
        {
          "xSupportShare": 0.925,
          "density": 0
        },
        {
          "xSupportShare": 0.9375,
          "density": 0
        },
        {
          "xSupportShare": 0.95,
          "density": 0
        },
        {
          "xSupportShare": 0.9625,
          "density": 0
        },
        {
          "xSupportShare": 0.975,
          "density": 0
        },
        {
          "xSupportShare": 0.9875,
          "density": 0
        },
        {
          "xSupportShare": 1,
          "density": 0
        }
      ]
    }
  ]
}
